Metadata-Version: 2.1
Name: confectionary-confetti
Version: 0.0.1
Summary: AWS SSM parameter store utility.
Home-page: https://github.com/AmberEngine/confectionary-confetti
License: UNKNOWN
Platform: UNKNOWN
